fastselenium/__init__.py
fastselenium-0.0.6.dist-info/LICENSE
fastselenium-0.0.6.dist-info/METADATA
fastselenium-0.0.6.dist-info/WHEEL
fastselenium-0.0.6.dist-info/top_level.txt
fastselenium-0.0.6.dist-info/RECORD
