Metadata-Version: 2.1
Name: fastselenium
Version: 0.0.6
Summary: make it easy to use selenium
Home-page: https://gitee.com/ZeroSeeker/fastselenium
Author: ZeroSeeker
Author-email: zeroseeker@foxmail.com
Classifier: Programming Language :: Python :: 3
Classifier: License :: OSI Approved :: MIT License
Classifier: Operating System :: OS Independent
License-File: LICENSE
Requires-Dist: pyperclip==1.8.1
Requires-Dist: selenium>=4.0.0
Requires-Dist: showlog>=0.0.6
Requires-Dist: requests>=2.31.0
